Arquitetura 1/Exercicio_Semana9/Exercicios_1/Guia_0901.v
// ---------------------------
// -- test clock generator (2)
// ---------------------------
module clock (output reg clk);
  initial begin
    clk = 1'b0;
  end
  always begin
    #12 clk = ~clk;  // Gera clock com período de 24 unidades de tempo
  end
endmodule

// ---------------------------
// -- pulse generator
// ---------------------------
module pulse (output reg signal, input clock);
  always @ (posedge clock) begin
    signal = 1'b1;
    #3 signal = 1'b0;
    #3 signal = 1'b1;
    #3 signal = 1'b0;
  end
endmodule

// ---------------------------
// -- trigger generator
// ---------------------------
module trigger (output reg signal, input on, input clock);
  always @ (posedge clock) begin
    if (on) begin
      #60 signal = 1'b1;
      #60 signal = 1'b0;
    end
  end
endmodule

// ---------------------------
// -- Guia_0901 Testbench
// ---------------------------
module Guia_0901;
  wire clock;
  reg p;
  wire p1, t1;

  // Instanciar clock, pulse e trigger
  clock clk (clock);
  pulse pulse1 (p1, clock);
  trigger trigger1 (t1, p, clock);

  initial begin
    p = 1'b0;
  end

  initial begin
    $dumpfile("Guia_0901.vcd");  // Arquivo de saída para o GTKWave
    $dumpvars(1, clock, p1, p, t1);

    #60  p = 1'b1;
    #120 p = 1'b0;
    #180 p = 1'b1;
    #240 p = 1'b0;
    #300 p = 1'b1;
    #360 p = 1'b0;
    #376 $finish;  // Termina a simulação
  end
endmodule

Arquitetura 1/Exercicio_Semana9/Exercicios_2/Guia_0902.v
`include "clock.v"  // Inclui o módulo clock a partir do arquivo separado

// ---------------------------
// -- pulse1 generator
// ---------------------------
module pulse1 (output reg signal, input clock);
  always @ (posedge clock) begin
    signal = 1'b1;
    #4 signal = 1'b0;
    #4 signal = 1'b1;
    #4 signal = 1'b0;
    #4 signal = 1'b1;
    #4 signal = 1'b0;
  end
endmodule

// ---------------------------
// -- pulse2 generator
// ---------------------------
module pulse2 (output reg signal, input clock);
  always @ (posedge clock) begin
    signal = 1'b1;
    #5 signal = 1'b0;
  end
endmodule

// ---------------------------
// -- pulse3 generator
// ---------------------------
module pulse3 (output reg signal, input clock);
  always @ (negedge clock) begin
    signal = 1'b1;
    #15 signal = 1'b0;
    #15 signal = 1'b1;
  end
endmodule

// ---------------------------
// -- pulse4 generator
// ---------------------------
module pulse4 (output reg signal, input clock);
  always @ (negedge clock) begin
    signal = 1'b1;
    #20 signal = 1'b0;
    #20 signal = 1'b1;
    #20 signal = 1'b0;
  end
endmodule

// ---------------------------
// -- Guia_0902 Testbench
// ---------------------------
module Guia_0902;
  wire clock;
  wire p1, p2, p3, p4;

  // Instanciar o gerador de clock e os geradores de pulsos
  clock clk (clock);
  pulse1 pls1 (p1, clock);
  pulse2 pls2 (p2, clock);
  pulse3 pls3 (p3, clock);
  pulse4 pls4 (p4, clock);

  initial begin
    $dumpfile("Guia_0902.vcd");  // Arquivo de saída para o GTKWave
    $dumpvars(1, clock, p1, p2, p3, p4);
    #480 $finish;  // Duração da simulação
  end
endmodule

Arquitetura 1/Exercicio_Semana9/Exercicios_2/Guia_0902.vcd
$date
	Sun Oct 06 16:34:27 2024
$end
$version
	Icarus Verilog
$end
$timescale
	1s
$end
$scope module Guia_0902 $end
$var wire 1 ! clock $end
$upscope $end
$scope module Guia_0902 $end
$var wire 1 " p1 $end
$upscope $end
$scope module Guia_0902 $end
$var wire 1 # p2 $end
$upscope $end
$scope module Guia_0902 $end
$var wire 1 $ p3 $end
$upscope $end
$scope module Guia_0902 $end
$var wire 1 % p4 $end
$upscope $end
$enddefinitions $end
$comment Show the parameter values. $end
$dumpall
$end
#0
$dumpvars
x%
x$
x#
x"
0!
$end
#12
1"
1#
1!
#16
0"
#17
0#
#20
1"
#24
1$
1%
0"
0!
#28
1"
#32
0"
#36
1#
1"
1!
#39
0$
#40
0"
#41
0#
#44
1"
0%
#48
0"
0!
#52
1"
#54
1$
#56
0"
#60
1#
1"
1!
#64
0"
1%
#65
0#
#68
1"
#72
0"
0!
#76
1"
#80
0"
#84
1#
1"
1!
0%
#87
0$
#88
0"
#89
0#
#92
1"
#96
1%
0"
0!
#100
1"
#102
1$
#104
0"
#108
1#
1"
1!
#112
0"
#113
0#
#116
1"
0%
#120
0"
0!
#124
1"
#128
0"
#132
1#
1"
1!
#135
0$
#136
0"
1%
#137
0#
#140
1"
#144
0"
0!
#148
1"
#150
1$
#152
0"
#156
1#
1"
1!
0%
#160
0"
#161
0#
#164
1"
#168
1%
0"
0!
#172
1"
#176
0"
#180
1#
1"
1!
#183
0$
#184
0"
#185
0#
#188
1"
0%
#192
0"
0!
#196
1"
#198
1$
#200
0"
#204
1#
1"
1!
#208
0"
1%
#209
0#
#212
1"
#216
0"
0!
#220
1"
#224
0"
#228
1#
1"
1!
0%
#231
0$
#232
0"
#233
0#
#236
1"
#240
1%
0"
0!
#244
1"
#246
1$
#248
0"
#252
1#
1"
1!
#256
0"
#257
0#
#260
1"
0%
#264
0"
0!
#268
1"
#272
0"
#276
1#
1"
1!
#279
0$
#280
0"
1%
#281
0#
#284
1"
#288
0"
0!
#292
1"
#294
1$
#296
0"
#300
1#
1"
1!
0%
#304
0"
#305
0#
#308
1"
#312
1%
0"
0!
#316
1"
#320
0"
#324
1#
1"
1!
#327
0$
#328
0"
#329
0#
#332
1"
0%
#336
0"
0!
#340
1"
#342
1$
#344
0"
#348
1#
1"
1!
#352
0"
1%
#353
0#
#356
1"
#360
0"
0!
#364
1"
#368
0"
#372
1#
1"
1!
0%
#375
0$
#376
0"
#377
0#
#380
1"
#384
1%
0"
0!
#388
1"
#390
1$
#392
0"
#396
1#
1"
1!
#400
0"
#401
0#
#404
1"
0%
#408
0"
0!
#412
1"
#416
0"
#420
1#
1"
1!
#423
0$
#424
0"
1%
#425
0#
#428
1"
#432
0"
0!
#436
1"
#438
1$
#440
0"
#444
1#
1"
1!
0%
#448
0"
#449
0#
#452
1"
#456
1%
0"
0!
#460
1"
#464
0"
#468
1#
1"
1!
#471
0$
#472
0"
#473
0#
#476
1"
0%
#480
0"
0!
