Arquitetura 1/Exercicio_Semana9/Exercicios_1/Guia_0901.v
// ---------------------------
// -- test clock generator (2)
// ---------------------------
module clock (output reg clk);
  initial begin
    clk = 1'b0;
  end
  always begin
    #12 clk = ~clk;  // Gera clock com período de 24 unidades de tempo
  end
endmodule

// ---------------------------
// -- pulse generator
// ---------------------------
module pulse (output reg signal, input clock);
  always @ (posedge clock) begin
    signal = 1'b1;
    #3 signal = 1'b0;
    #3 signal = 1'b1;
    #3 signal = 1'b0;
  end
endmodule

// ---------------------------
// -- trigger generator
// ---------------------------
module trigger (output reg signal, input on, input clock);
  always @ (posedge clock) begin
    if (on) begin
      #60 signal = 1'b1;
      #60 signal = 1'b0;
    end
  end
endmodule

// ---------------------------
// -- Guia_0901 Testbench
// ---------------------------
module Guia_0901;
  wire clock;
  reg p;
  wire p1, t1;

  // Instanciar clock, pulse e trigger
  clock clk (clock);
  pulse pulse1 (p1, clock);
  trigger trigger1 (t1, p, clock);

  initial begin
    p = 1'b0;
  end

  initial begin
    $dumpfile("Guia_0901.vcd");  // Arquivo de saída para o GTKWave
    $dumpvars(1, clock, p1, p, t1);

    #60  p = 1'b1;
    #120 p = 1'b0;
    #180 p = 1'b1;
    #240 p = 1'b0;
    #300 p = 1'b1;
    #360 p = 1'b0;
    #376 $finish;  // Termina a simulação
  end
endmodule

Arquitetura 1/Exercicio_Semana9/Exercicios_1/Guia_0901.vcd
$date
	Sun Oct 06 16:29:44 2024
$end
$version
	Icarus Verilog
$end
$timescale
	1s
$end
$scope module Guia_0901 $end
$var wire 1 ! clock $end
$upscope $end
$scope module Guia_0901 $end
$var wire 1 " p1 $end
$upscope $end
$scope module Guia_0901 $end
$var reg 1 # p $end
$upscope $end
$scope module Guia_0901 $end
$var wire 1 $ t1 $end
$upscope $end
$enddefinitions $end
$comment Show the parameter values. $end
$dumpall
$end
#0
$dumpvars
x$
0#
x"
0!
$end
#12
1"
1!
#15
0"
#18
1"
#21
0"
#24
0!
#36
1"
1!
#39
0"
#42
1"
#45
0"
#48
0!
#60
1"
1!
1#
#63
0"
#66
1"
#69
0"
#72
0!
#84
1"
1!
#87
0"
#90
1"
#93
0"
#96
0!
#108
1"
1!
#111
0"
#114
1"
#117
0"
#120
0!
1$
#132
1"
1!
#135
0"
#138
1"
#141
0"
#144
0!
#156
1"
1!
#159
0"
#162
1"
#165
0"
#168
0!
#180
1"
1!
0$
0#
#183
0"
#186
1"
#189
0"
#192
0!
#204
1"
1!
#207
0"
#210
1"
#213
0"
#216
0!
#228
1"
1!
#231
0"
#234
1"
#237
0"
#240
0!
#252
1"
1!
#255
0"
#258
1"
#261
0"
#264
0!
#276
1"
1!
#279
0"
#282
1"
#285
0"
#288
0!
#300
1"
1!
#303
0"
#306
1"
#309
0"
#312
0!
#324
1"
1!
#327
0"
#330
1"
#333
0"
#336
0!
#348
1"
1!
#351
0"
#354
1"
#357
0"
#360
0!
1#
#372
1"
1!
#375
0"
#378
1"
#381
0"
#384
0!
#396
1"
1!
#399
0"
#402
1"
#405
0"
#408
0!
#420
1"
1!
#423
0"
#426
1"
#429
0"
#432
0!
1$
#444
1"
1!
#447
0"
#450
1"
#453
0"
#456
0!
#468
1"
1!
#471
0"
#474
1"
#477
0"
#480
0!
#492
1"
1!
0$
#495
0"
#498
1"
#501
0"
#504
0!
#516
1"
1!
#519
0"
#522
1"
#525
0"
#528
0!
#540
1"
1!
#543
0"
#546
1"
#549
0"
#552
0!
1$
#564
1"
1!
#567
0"
#570
1"
#573
0"
#576
0!
#588
1"
1!
#591
0"
#594
1"
#597
0"
#600
0!
0#
#612
1"
1!
0$
#615
0"
#618
1"
#621
0"
#624
0!
#636
1"
1!
#639
0"
#642
1"
#645
0"
#648
0!
#660
1"
1!
#663
0"
#666
1"
#669
0"
#672
0!
#684
1"
1!
#687
0"
#690
1"
#693
0"
#696
0!
#708
1"
1!
#711
0"
#714
1"
#717
0"
#720
0!
#732
1"
1!
#735
0"
#738
1"
#741
0"
#744
0!
#756
1"
1!
#759
0"
#762
1"
#765
0"
#768
0!
#780
1"
1!
#783
0"
#786
1"
#789
0"
#792
0!
#804
1"
1!
#807
0"
#810
1"
#813
0"
#816
0!
#828
1"
1!
#831
0"
#834
1"
#837
0"
#840
0!
#852
1"
1!
#855
0"
#858
1"
#861
0"
#864
0!
#876
1"
1!
#879
0"
#882
1"
#885
0"
#888
0!
#900
1"
1!
1#
#903
0"
#906
1"
#909
0"
#912
0!
#924
1"
1!
#927
0"
#930
1"
#933
0"
#936
0!
#948
1"
1!
#951
0"
#954
1"
#957
0"
#960
0!
1$
#972
1"
1!
#975
0"
#978
1"
#981
0"
#984
0!
#996
1"
1!
#999
0"
#1002
1"
#1005
0"
#1008
0!
#1020
1"
1!
0$
#1023
0"
#1026
1"
#1029
0"
#1032
0!
#1044
1"
1!
#1047
0"
#1050
1"
#1053
0"
#1056
0!
#1068
1"
1!
#1071
0"
#1074
1"
#1077
0"
#1080
0!
1$
#1092
1"
1!
#1095
0"
#1098
1"
#1101
0"
#1104
0!
#1116
1"
1!
#1119
0"
#1122
1"
#1125
0"
#1128
0!
#1140
1"
1!
0$
#1143
0"
#1146
1"
#1149
0"
#1152
0!
#1164
1"
1!
#1167
0"
#1170
1"
#1173
0"
#1176
0!
#1188
1"
1!
#1191
0"
#1194
1"
#1197
0"
#1200
0!
1$
#1212
1"
1!
#1215
0"
#1218
1"
#1221
0"
#1224
0!
#1236
1"
1!
#1239
0"
#1242
1"
#1245
0"
#1248
0!
#1260
1"
1!
0$
0#
#1263
0"
#1266
1"
#1269
0"
#1272
0!
#1284
1"
1!
#1287
0"
#1290
1"
#1293
0"
#1296
0!
#1308
1"
1!
#1311
0"
#1314
1"
#1317
0"
#1320
0!
#1332
1"
1!
#1335
0"
#1338
1"
#1341
0"
#1344
0!
#1356
1"
1!
#1359
0"
#1362
1"
#1365
0"
#1368
0!
#1380
1"
1!
#1383
0"
#1386
1"
#1389
0"
#1392
0!
#1404
1"
1!
#1407
0"
#1410
1"
#1413
0"
#1416
0!
#1428
1"
1!
#1431
0"
#1434
1"
#1437
0"
#1440
0!
#1452
1"
1!
#1455
0"
#1458
1"
#1461
0"
#1464
0!
#1476
1"
1!
#1479
0"
#1482
1"
#1485
0"
#1488
0!
#1500
1"
1!
#1503
0"
#1506
1"
#1509
0"
#1512
0!
#1524
1"
1!
#1527
0"
#1530
1"
#1533
0"
#1536
0!
#1548
1"
1!
#1551
0"
#1554
1"
#1557
0"
#1560
0!
#1572
1"
1!
#1575
0"
#1578
1"
#1581
0"
#1584
0!
#1596
1"
1!
#1599
0"
#1602
1"
#1605
0"
#1608
0!
#1620
1"
1!
#1623
0"
#1626
1"
#1629
0"
